{
  "body1.png": {
    "palette": "{modDir}/sprite/patch/palette74",
    "raster": "{modDir}/sprite/patch/raster113"
  },
  "body2.png": {
    "palette": "{modDir}/sprite/patch/palette74",
    "raster": "{modDir}/sprite/patch/raster114"
  },
  "body3.png": {
    "palette": "{modDir}/sprite/patch/palette74",
    "raster": "{modDir}/sprite/patch/raster115"
  },
  "body4.png": {
    "palette": "{modDir}/sprite/patch/palette74",
    "raster": "{modDir}/sprite/patch/raster116"
  },
  "dizzy1.png": {
    "palette": "{modDir}/sprite/patch/palette74",
    "raster": "{modDir}/sprite/patch/raster117"
  },
  "dizzy2.png": {
    "palette": "{modDir}/sprite/patch/palette74",
    "raster": "{modDir}/sprite/patch/raster118"
  },
  "dizzy3.png": {
    "palette": "{modDir}/sprite/patch/palette74",
    "raster": "{modDir}/sprite/patch/raster119"
  },
  "leftwing1.png": {
    "palette": "{modDir}/sprite/patch/palette74",
    "raster": "{modDir}/sprite/patch/raster120"
  },
  "leftwing2.png": {
    "palette": "{modDir}/sprite/patch/palette74",
    "raster": "{modDir}/sprite/patch/raster121"
  },
  "leftwing3.png": {
    "palette": "{modDir}/sprite/patch/palette74",
    "raster": "{modDir}/sprite/patch/raster122"
  },
  "leftwing4.png": {
    "palette": "{modDir}/sprite/patch/palette74",
    "raster": "{modDir}/sprite/patch/raster123"
  },
  "pain.png": {
    "palette": "{modDir}/sprite/patch/palette74",
    "raster": "{modDir}/sprite/patch/raster124"
  },
  "pain2.png": {
    "palette": "{modDir}/sprite/patch/palette74",
    "raster": "{modDir}/sprite/patch/raster125"
  },
  "rightwing1.png": {
    "palette": "{modDir}/sprite/patch/palette74",
    "raster": "{modDir}/sprite/patch/raster126"
  },
  "rightwing2.png": {
    "palette": "{modDir}/sprite/patch/palette74",
    "raster": "{modDir}/sprite/patch/raster127"
  },
  "rightwing3.png": {
    "palette": "{modDir}/sprite/patch/palette74",
    "raster": "{modDir}/sprite/patch/raster128"
  },
  "rightwing4.png": {
    "palette": "{modDir}/sprite/patch/palette74",
    "raster": "{modDir}/sprite/patch/raster129"
  },
  "sleep.png": {
    "palette": "{modDir}/sprite/patch/palette74",
    "raster": "{modDir}/sprite/patch/raster130"
  }
}